tubedrive/__init__.py
tubedrive/models.py
tubedrive/runner.py
tubedrive/utils.py
tubedrive/youtube_helper.py
tubedrive-0.1.2.dist-info/entry_points.txt
tubedrive-0.1.2.dist-info/METADATA
tubedrive-0.1.2.dist-info/WHEEL
tubedrive-0.1.2.dist-info/RECORD
