Metadata-Version: 2.1
Name: tubedrive
Version: 0.1.2
Summary: Use youtube as a storage
Author: Mayas Nova
Requires-Python: >=3.9,<4.0
Classifier: Programming Language :: Python :: 3
Classifier: Programming Language :: Python :: 3.9
Classifier: Programming Language :: Python :: 3.10
Classifier: Programming Language :: Python :: 3.11
Classifier: Programming Language :: Python :: 3.12
Requires-Dist: google-api-python-client (>=2.119.0,<3.0.0)
Requires-Dist: google-auth-oauthlib (>=1.2.0,<2.0.0)
Requires-Dist: moviepy (>=1.0.3,<2.0.0)
Requires-Dist: skinny-orm (==0.1.2)
Requires-Dist: typer[all] (>=0.9.0,<0.10.0)
